LICENSE
MANIFEST.in
README.md
requirements.txt
setup.py
test/test_core.py
test/test_projection.py
test/test_pvestimation.py
test/test_resampling.py
toblerone/__init__.py
toblerone/__main__.py
toblerone/_version.py
toblerone/core.py
toblerone/icosphere.py
toblerone/projection.py
toblerone/scripts.py
toblerone/surface_estimators.py
toblerone/utils.py
toblerone.egg-info/PKG-INFO
toblerone.egg-info/SOURCES.txt
toblerone.egg-info/dependency_links.txt
toblerone.egg-info/entry_points.txt
toblerone.egg-info/requires.txt
toblerone.egg-info/top_level.txt
toblerone/classes/__init__.py
toblerone/classes/common_parser.py
toblerone/classes/surfaces.py