Metadata-Version: 2.1
Name: toblerone
Version: 0.10.1
Summary: Surface-based analysis tools
Home-page: https://bitbucket.org/quantified-imaging/toblerone
Author: Tom Kirk
Author-email: thomas.kirk@quantified-imaging.com
License: Custom license (see LICENSE.md)
License-File: LICENSE
Requires-Dist: nibabel
Requires-Dist: numpy
Requires-Dist: scipy>=1.8
Requires-Dist: regtricks
Requires-Dist: pyvista
Requires-Dist: h5py
Requires-Dist: vtk
Requires-Dist: trimesh
Requires-Dist: rtree
Requires-Dist: numba
